get_user_information/__init__.py
get_user_information/ip_master.py
get_user_information/system_info_checker.py
getuserinformation-0.0.2.dist-info/LICENSE
getuserinformation-0.0.2.dist-info/METADATA
getuserinformation-0.0.2.dist-info/WHEEL
getuserinformation-0.0.2.dist-info/top_level.txt
getuserinformation-0.0.2.dist-info/RECORD
